{
  "main": {
    "id": "951bd256c7b6ac57",
    "type": "split",
    "children": [
      {
        "id": "fa60ef4d1bce55d4",
        "type": "tabs",
        "children": [
          {
            "id": "14150c15228e191a",
            "type": "leaf",
            "state": {
              "type": "empty",
              "state": {},
              "icon": "lucide-file",
              "title": "New tab"
            }
          }
        ]
      }
    ],
    "direction": "vertical"
  },
  "left": {
    "id": "9f9e35574bc4f77f",
    "type": "split",
    "children": [
      {
        "id": "52cfdd4d1d422642",
        "type": "tabs",
        "children": [
          {
            "id": "2fa732bb26c9cab8",
            "type": "leaf",
            "state": {
              "type": "file-explorer",
              "state": {
                "sortOrder": "alphabetical",
                "autoReveal": false
              },
              "icon": "lucide-folder-closed",
              "title": "Files"
            }
          },
          {
            "id": "3769fb4146c726d1",
            "type": "leaf",
            "state": {
              "type": "search",
              "state": {
                "query": "pasted",
                "matchingCase": false,
                "explainSearch": true,
                "collapseAll": true,
                "extraContext": false,
                "sortOrder": "alphabetical"
              },
              "icon": "lucide-search",
              "title": "Search"
            }
          },
          {
            "id": "6675b6059d766882",
            "type": "leaf",
            "state": {
              "type": "bookmarks",
              "state": {},
              "icon": "lucide-bookmark",
              "title": "Bookmarks"
            }
          }
        ]
      }
    ],
    "direction": "horizontal",
    "width": 516.5
  },
  "right": {
    "id": "9182d54996f9165f",
    "type": "split",
    "children": [
      {
        "id": "4f4266bdc90354f7",
        "type": "tabs",
        "children": [
          {
            "id": "de9364380d39fc33",
            "type": "leaf",
            "state": {
              "type": "backlink",
              "state": {
                "file": "notes/2025/01.md",
                "collapseAll": false,
                "extraContext": false,
                "sortOrder": "alphabetical",
                "showSearch": false,
                "searchQuery": "",
                "backlinkCollapsed": false,
                "unlinkedCollapsed": true
              },
              "icon": "links-coming-in",
              "title": "Backlinks for 01"
            }
          },
          {
            "id": "feb58a63ff6b77df",
            "type": "leaf",
            "state": {
              "type": "outgoing-link",
              "state": {
                "file": "notes/2025/01.md",
                "linksCollapsed": false,
                "unlinkedCollapsed": true
              },
              "icon": "links-going-out",
              "title": "Outgoing links from 01"
            }
          },
          {
            "id": "d1f1896ab312933c",
            "type": "leaf",
            "state": {
              "type": "tag",
              "state": {
                "sortOrder": "frequency",
                "useHierarchy": true,
                "showSearch": false,
                "searchQuery": ""
              },
              "icon": "lucide-tags",
              "title": "Tags"
            }
          },
          {
            "id": "62ef2ac517635692",
            "type": "leaf",
            "state": {
              "type": "outline",
              "state": {
                "file": "notes/2025/01.md",
                "followCursor": false,
                "showSearch": false,
                "searchQuery": ""
              },
              "icon": "lucide-list",
              "title": "Outline of 01"
            }
          }
        ]
      }
    ],
    "direction": "horizontal",
    "width": 300,
    "collapsed": true
  },
  "left-ribbon": {
    "hiddenItems": {
      "bases:Create new base": false,
      "switcher:Open quick switcher": false,
      "graph:Open graph view": false,
      "canvas:Create new canvas": false,
      "daily-notes:Open today's daily note": false,
      "templates:Insert template": false,
      "command-palette:Open command palette": false,
      "zk-prefixer:Create new unique note": false
    }
  },
  "active": "14150c15228e191a",
  "lastOpenFiles": [
    "resources/_gen/images/images/virgin-hit-by-thunderbolt-fall-off-horse_hu_a387dd7fa3bc5d36.jpg",
    "resources/_gen/images/images/virgin-hit-by-thunderbolt-fall-off-horse_hu_81e19a23ce975a30.jpg",
    "resources/_gen/images/images/virgin-hit-by-thunderbolt-fall-off-horse_hu_35780e9737fa0b1f.jpg",
    "resources/_gen/images/images/share_frame1200x627-630x627_hu_d98bef6a8fc4b592.png",
    "resources/_gen/images/images/share_frame1200x627-630x627_hu_7421a5f331ee799d.png",
    "resources/_gen/images/images/basic_meta_6_hu_c4cecd52474cc2c5.png",
    "resources/_gen/images/images/basic_meta_6_hu_76047d8aec83e417.png",
    "public/software/site-build/book-cover-test/layout-vintage/well-described/index.html",
    "public/software/site-build/book-cover-test/layout-vintage/simple-image/index.html",
    "public/software/site-build/book-cover-test/layout-vintage/over-stuffed/index.html",
    "public/software/site-build/book-cover-test/layout-vintage/back-to-basics/index.html",
    "public/software/site-build/book-cover-test/layout-notebook/well-described/index.html",
    "public/software/site-build/book-cover-test/layout-notebook/simple-image/index.html",
    "public/software/site-build/book-cover-test/layout-notebook/over-stuffed/index.html",
    "public/software/site-build/book-cover-test/layout-notebook/back-to-basics/index.html",
    "public/software/site-build/book-cover-test/layout-modern/well-described/index.html",
    "public/software/site-build/book-cover-test/layout-modern/simple-image/index.html",
    "public/images/tweets_media/999916255007002626-DeBqd4AV4AE7Asl_hu_f9f813366be38f9.jpg",
    "public/images/tweets_media/999916255007002626-DeBqd4AV4AE7Asl_hu_f329aa5dae5fea9f.jpg",
    "public/images/tweets_media/999916255007002626-DeBqd4AV4AE7Asl_hu_ef8666b9b7589bc3.jpg",
    "public/images/tweets_media/999916255007002626-DeBqd4AV4AE7Asl_hu_156d93850b1715d8.jpg",
    "node_modules/tar/node_modules/fs-minipass/node_modules/minipass/README.md",
    "node_modules/socks/docs/examples/typescript/connectExample.md",
    "node_modules/socks/docs/examples/typescript/bindExample.md",
    "node_modules/socks/docs/examples/typescript/associateExample.md",
    "node_modules/socks/docs/examples/javascript/connectExample.md",
    "node_modules/socks/docs/examples/javascript/bindExample.md",
    "node_modules/socks/docs/examples/javascript/associateExample.md",
    "node_modules/re2/vendor/abseil-cpp/CMake/README.md",
    "node_modules/puppeteer-core/src/bidi/core/README.md",
    "node_modules/@puppeteer/browsers/node_modules/ms/readme.md",
    "node_modules/@puppeteer/browsers/node_modules/ms/license.md",
    "node_modules/@puppeteer/browsers/node_modules/debug/README.md",
    "node_modules/@npmcli/agent/node_modules/lru-cache/README.md",
    "node_modules/@isaacs/cliui/node_modules/wrap-ansi/readme.md",
    "node_modules/@isaacs/cliui/node_modules/strip-ansi/readme.md",
    "node_modules/@isaacs/cliui/node_modules/string-width/readme.md",
    "node_modules/@isaacs/cliui/node_modules/ansi-styles/readme.md",
    "node_modules/@isaacs/cliui/node_modules/emoji-regex/README.md",
    "node_modules/@isaacs/cliui/node_modules/ansi-regex/readme.md",
    "node_modules/tar/node_modules/minipass/README.md",
    "node_modules/tar/node_modules/fs-minipass/README.md",
    "node_modules/sshpk/node_modules/jsbn/README.md",
    "node_modules/socks-proxy-agent/node_modules/ms/readme.md",
    "node_modules/socks-proxy-agent/node_modules/ms/license.md",
    "node_modules/socks-proxy-agent/node_modules/debug/README.md"
  ]
}